{
   "bergen" : {
      "color" : "#EFB143",
      "mapHeight" : "250px",
      "mapWidth" : "550px",
      "publish" : true,
      "runInfo" : "Detour for June 18: left to go South on Franklin, then right to go West on Prospect Pl/Warren St with turns on 4th Ave, Bond, & Smith.",
      "detour": true,
      "detourInfo": "Note: Route is changed for June 18! West on Prospect Pl/Warren St after Franklin Ave",
      "title" : "Bergen Bike Bus",
      "trackerBounds" : {
         "bottomLeft" : [
            40.685828,
            -73.91115
         ],
         "topRight" : [
            40.667982,
            -73.991364
         ]
      },
      "combinedRouteKeys" : ["bergen-to-court", "bergen-to-ps372"]
   }
}
